{
  "timestamp": "2025-09-05T16:19:33.919Z",
  "sessionId": "746227f3-4049-4323-a81e-71989aad03fc",
  "clientProfile": {
    "budget": 100000,
    "location": "Worcester MA",
    "monthlyIncome": 2000
  },
  "metrics": {
    "priceBands": {
      "singleFamily": {
        "min": 382500,
        "max": 517500,
        "sourceIds": [
          "research_0"
        ]
      },
      "multiFamily": {
        "min": 369750,
        "max": 500250,
        "sourceIds": [
          "research_1"
        ]
      }
    },
    "rentBands": {
      "point2Br": {
        "value": 2057,
        "sourceId": "research_2"
      },
      "twoBr": {
        "min": 1001,
        "max": 2444,
        "sourceIds": [
          "research_9"
        ]
      }
    },
    "market": {
      "city": "Worcester MA",
      "domDays": {
        "min": 12,
        "max": 128,
        "sourceIds": [
          "research_10"
        ]
      },
      "salePsf": {
        "min": 271,
        "max": 292,
        "sourceIds": [
          "research_11"
        ]
      }
    },
    "rates": {
      "sourceIds": [
        "research_3",
        "research_4"
      ],
      "conventional": 0.0638,
      "fha": 0.0575
    }
  },
  "output": {
    "brief": "Professional investment strategies for Worcester MA with $100000 capital",
    "market": {
      "city": "Worcester MA",
      "focus_neighborhoods": [],
      "demand_signals": []
    },
    "strategies": [
      {
        "name": "Multi-Family Cashflow Strategy",
        "objective": "Maximize rental income through 2-4 unit properties",
        "buy_box": {
          "property_types": [
            "2 Family",
            "3 Family",
            "4 Family"
          ],
          "submarkets": [
            "Downtown",
            "University District"
          ],
          "zoning_required": [
            "R2",
            "R3"
          ],
          "lot_constraints": {
            "min_lot_sqft": null,
            "setbacks_notes": "Standard residential"
          },
          "building_constraints": {
            "min_ceiling_ft": null,
            "egress_req": "Two exits per unit",
            "parking": "Off-street preferred"
          },
          "proximity": [
            {
              "to": "Employment centers",
              "within_miles": 5
            }
          ],
          "price_band_usd": {
            "min": 163265,
            "max": 408163
          },
          "beds_baths_min": {
            "beds": 2,
            "baths": 1
          },
          "exclude_flags": [
            "major repairs",
            "foundation issues"
          ]
        },
        "evaluation_rules": {
          "min_cap_rate_pct": null,
          "min_monthly_cashflow_usd": null,
          "min_dscr_base": null,
          "fha_self_sufficiency_rule": {
            "required": false,
            "note": ""
          },
          "strategy_specific_metrics": []
        },
        "financing": {
          "primary": {
            "type": "Conventional",
            "notes": "30-year fixed 6.38% (source: research_3, research_4)"
          },
          "alternatives": [
            "FHA House-Hack",
            "DSCR"
          ]
        },
        "comps_bands": {
          "rent": [
            {
              "unit_type": "2br",
              "range_monthly": [
                1001,
                2444
              ],
              "notes": "",
              "sources": [
                "research_9"
              ]
            }
          ],
          "sale_psf": {
            "range": [
              271,
              292
            ],
            "sources": [
              "research_11"
            ]
          },
          "dom_band": {
            "range_days": [
              12,
              128
            ],
            "notes": "",
            "sources": [
              "research_10"
            ]
          }
        },
        "execution": {
          "typical_stabilization_months": 3,
          "top_risks": [
            "vacancy",
            "maintenance"
          ],
          "mitigation_playbook": [
            "thorough screening",
            "preventive maintenance"
          ]
        },
        "handoff_checklist": [
          "property inspection",
          "rental market analysis"
        ],
        "scorecard": {
          "liquidity_0_20": 15,
          "cashflow_quality_0_25": 20,
          "execution_risk_0_25": 15,
          "location_durability_0_15": 10,
          "strategic_fit_0_15": 10,
          "rationale": "Based on market metrics"
        },
        "status": "READY",
        "search_space": {
          "absolute_range": {
            "min": 163265,
            "max": 408163
          },
          "sweet_spot": {
            "min": 314287,
            "max": 625313,
            "note": "Statistical center - reference only"
          },
          "dynamic_gates": {
            "base_cap_rate": 0.065,
            "base_coc": 0.08,
            "base_dscr": 1.25,
            "cap_rate_slope": 0.1,
            "coc_slope": 0.2,
            "dscr_floor": 1.2
          },
          "evaluation_directive": "COMPREHENSIVE",
          "market_context": {
            "median_price": 435000
          }
        },
        "evaluation_directive": "COMPREHENSIVE",
        "market_context": {
          "median_price": 435000,
          "market_band_usd": {
            "min": 369750,
            "max": 500250,
            "source": "multiFamily"
          },
          "affordability_band_usd": {
            "min": 163265,
            "max": 408163,
            "notes": [
              "20% down, closing≈3.5%"
            ]
          }
        }
      },
      {
        "name": "Single-Family Appreciation Focus",
        "objective": "Focus on appreciation through single-family homes in emerging neighborhoods",
        "buy_box": {
          "property_types": [
            "Single Family"
          ],
          "submarkets": [
            "Eastside",
            "South Worcester"
          ],
          "zoning_required": [
            "R1"
          ],
          "lot_constraints": {
            "min_lot_sqft": null,
            "setbacks_notes": "Conform to neighborhood"
          },
          "building_constraints": {
            "min_ceiling_ft": null,
            "egress_req": "Standard residential",
            "parking": "Garage or driveway"
          },
          "proximity": [
            {
              "to": "Schools",
              "within_miles": 2
            }
          ],
          "price_band_usd": {
            "min": 163265,
            "max": 408163
          },
          "beds_baths_min": {
            "beds": 3,
            "baths": 2
          },
          "exclude_flags": [
            "in flood zones",
            "heavy rehab required"
          ]
        },
        "evaluation_rules": {
          "min_cap_rate_pct": null,
          "min_monthly_cashflow_usd": null,
          "min_dscr_base": null,
          "fha_self_sufficiency_rule": {
            "required": false,
            "note": "Not applicable"
          },
          "strategy_specific_metrics": [
            "historical appreciation rates"
          ]
        },
        "financing": {
          "primary": {
            "type": "Conventional",
            "notes": "30-year fixed 6.38% (source: research_3, research_4)"
          },
          "alternatives": [
            "HELOC",
            "Bridge Loan"
          ]
        },
        "comps_bands": {
          "rent": [
            {
              "unit_type": "2br",
              "range_monthly": [
                1001,
                2444
              ],
              "notes": "",
              "sources": [
                "research_9"
              ]
            }
          ],
          "sale_psf": {
            "range": [
              271,
              292
            ],
            "sources": [
              "research_11"
            ]
          },
          "dom_band": {
            "range_days": [
              12,
              128
            ],
            "notes": "",
            "sources": [
              "research_10"
            ]
          }
        },
        "execution": {
          "typical_stabilization_months": 6,
          "top_risks": [
            "market downturn",
            "high vacancy"
          ],
          "mitigation_playbook": [
            "diversified tenant base",
            "long-term leases"
          ]
        },
        "handoff_checklist": [
          "title review",
          "neighborhood trend analysis"
        ],
        "scorecard": {
          "liquidity_0_20": 15,
          "cashflow_quality_0_25": 20,
          "execution_risk_0_25": 15,
          "location_durability_0_15": 10,
          "strategic_fit_0_15": 10,
          "rationale": "Based on market metrics"
        },
        "status": "READY",
        "search_space": {
          "absolute_range": {
            "min": 163265,
            "max": 408163
          },
          "sweet_spot": {
            "min": 314287,
            "max": 625313,
            "note": "Statistical center - reference only"
          },
          "dynamic_gates": {
            "base_cap_rate": 0.065,
            "base_coc": 0.08,
            "base_dscr": 1.25,
            "cap_rate_slope": 0.1,
            "coc_slope": 0.2,
            "dscr_floor": 1.2
          },
          "evaluation_directive": "COMPREHENSIVE",
          "market_context": {
            "median_price": 435000
          }
        },
        "evaluation_directive": "COMPREHENSIVE",
        "market_context": {
          "median_price": 435000,
          "market_band_usd": {
            "min": 369750,
            "max": 500250,
            "source": "multiFamily"
          },
          "affordability_band_usd": {
            "min": 163265,
            "max": 408163,
            "notes": [
              "20% down, closing≈3.5%"
            ]
          }
        }
      },
      {
        "name": "Commercial Mixed-Use Strategy",
        "objective": "Invest in mixed-use properties for diversified income streams",
        "buy_box": {
          "property_types": [
            "Mixed-Use"
          ],
          "submarkets": [
            "Downtown",
            "Canal District"
          ],
          "zoning_required": [
            "MU"
          ],
          "lot_constraints": {
            "min_lot_sqft": null,
            "setbacks_notes": "According to commercial requirements"
          },
          "building_constraints": {
            "min_ceiling_ft": null,
            "egress_req": "Commercial code compliant",
            "parking": "Public or shared parking"
          },
          "proximity": [
            {
              "to": "Public transport",
              "within_miles": 1
            }
          ],
          "price_band_usd": {
            "min": 163265,
            "max": 408163
          },
          "beds_baths_min": {
            "beds": 1,
            "baths": 1
          },
          "exclude_flags": [
            "environmental issues",
            "major structural concerns"
          ]
        },
        "evaluation_rules": {
          "min_cap_rate_pct": null,
          "min_monthly_cashflow_usd": null,
          "min_dscr_base": null,
          "fha_self_sufficiency_rule": {
            "required": false,
            "note": "Not applicable"
          },
          "strategy_specific_metrics": [
            "commercial occupancy rates"
          ]
        },
        "financing": {
          "primary": {
            "type": "Conventional",
            "notes": "30-year fixed 6.38% (source: research_3, research_4)"
          },
          "alternatives": [
            "SBA 504",
            "Commercial Bridge Loan"
          ]
        },
        "comps_bands": {
          "rent": [
            {
              "unit_type": "2br",
              "range_monthly": [
                1001,
                2444
              ],
              "notes": "",
              "sources": [
                "research_9"
              ]
            }
          ],
          "sale_psf": {
            "range": [
              271,
              292
            ],
            "sources": [
              "research_11"
            ]
          },
          "dom_band": {
            "range_days": [
              12,
              128
            ],
            "notes": "",
            "sources": [
              "research_10"
            ]
          }
        },
        "execution": {
          "typical_stabilization_months": 12,
          "top_risks": [
            "tenant turnover",
            "regulatory changes"
          ],
          "mitigation_playbook": [
            "lease diversification",
            "regular market assessments"
          ]
        },
        "handoff_checklist": [
          "environmental assessment",
          "commercial lease review"
        ],
        "scorecard": {
          "liquidity_0_20": 15,
          "cashflow_quality_0_25": 20,
          "execution_risk_0_25": 15,
          "location_durability_0_15": 10,
          "strategic_fit_0_15": 10,
          "rationale": "Based on market metrics"
        },
        "status": "READY",
        "search_space": {
          "absolute_range": {
            "min": 163265,
            "max": 408163
          },
          "sweet_spot": {
            "min": 325125,
            "max": 646875,
            "note": "Statistical center - reference only"
          },
          "dynamic_gates": {
            "base_cap_rate": 0.065,
            "base_coc": 0.08,
            "base_dscr": 1.25,
            "cap_rate_slope": 0.1,
            "coc_slope": 0.2,
            "dscr_floor": 1.2
          },
          "evaluation_directive": "COMPREHENSIVE",
          "market_context": {
            "median_price": 450000
          }
        },
        "evaluation_directive": "COMPREHENSIVE",
        "market_context": {
          "median_price": 450000,
          "market_band_usd": {
            "min": 382500,
            "max": 517500,
            "source": "singleFamily"
          },
          "affordability_band_usd": {
            "min": 163265,
            "max": 408163,
            "notes": [
              "20% down, closing≈3.5%"
            ]
          }
        }
      }
    ],
    "research_log": [
      "What is the current median price for single-family homes in Worcester MA? → 450000",
      "What is the current median price for 2-4 unit properties in Worcester MA? → 435000",
      "What is the average rent for a 2-bedroom apartment in Worcester MA? → 2057",
      "What is the current 30-year conventional mortgage rate for investment properties in Worcester MA? → 6.38",
      "What is the current FHA mortgage interest rate in Worcester MA? → 5.75",
      "What is the FHA loan limit for properties in Worcester MA? → 806500",
      "What is the current vacancy rate for rental properties in Worcester MA? → 1.7",
      "What is the current property tax rate in Worcester MA? → 13.19",
      "What is the average cost of property insurance for investment properties in Worcester MA? → 2008",
      "What is the range of rent prices for 2-bedroom apartments in Worcester MA? → {\"min\":1001,\"max\":2444}",
      "What is the range of days on market for properties in Worcester MA? → {\"min\":12,\"max\":128}",
      "What is the range of price per square foot for properties in Worcester MA? → {\"min\":271,\"max\":292}"
    ]
  }
}